eagerx_interbotix/__init__.py
eagerx_interbotix/aruco_detector.py
eagerx_interbotix/camera/__init__.py
eagerx_interbotix/camera/assets/realsense2_d435.urdf
eagerx_interbotix/camera/calibration.py
eagerx_interbotix/camera/enginestates.py
eagerx_interbotix/camera/objects.py
eagerx_interbotix/camera/pybullet/enginenodes.py
eagerx_interbotix/env.py
eagerx_interbotix/goal_env.py
eagerx_interbotix/ik/__init__.py
eagerx_interbotix/ik/node.py
eagerx_interbotix/overlay/__init__.py
eagerx_interbotix/overlay/node.py
eagerx_interbotix/reset/__init__.py
eagerx_interbotix/reset/node.py
eagerx_interbotix/safety/__init__.py
eagerx_interbotix/safety/collision.py
eagerx_interbotix/safety/node.py
eagerx_interbotix/safety/workspaces.py
eagerx_interbotix/solid/__init__.py
eagerx_interbotix/solid/assets/box.urdf
eagerx_interbotix/solid/assets/box_goal.urdf
eagerx_interbotix/solid/assets/can.urdf
eagerx_interbotix/solid/assets/can_goal.urdf
eagerx_interbotix/solid/assets/circle_goal.urdf
eagerx_interbotix/solid/assets/surface.urdf
eagerx_interbotix/solid/assets/table/table.mtl
eagerx_interbotix/solid/assets/table/table.obj
eagerx_interbotix/solid/assets/table/table.png
eagerx_interbotix/solid/assets/table/table.urdf
eagerx_interbotix/solid/goal.py
eagerx_interbotix/solid/pybullet/enginestates.py
eagerx_interbotix/solid/real/__init__.py
eagerx_interbotix/solid/real/enginenodes.py
eagerx_interbotix/solid/real/enginestates.py
eagerx_interbotix/solid/solid.py
eagerx_interbotix/solid/yaw_node.py
eagerx_interbotix/utils.py
eagerx_interbotix/xseries/__init__.py
eagerx_interbotix/xseries/assets/config/mobile_px100.yaml
eagerx_interbotix/xseries/assets/config/mobile_wx200.yaml
eagerx_interbotix/xseries/assets/config/mobile_wx250s.yaml
eagerx_interbotix/xseries/assets/config/modes.yaml
eagerx_interbotix/xseries/assets/config/px100.yaml
eagerx_interbotix/xseries/assets/config/px150.yaml
eagerx_interbotix/xseries/assets/config/rx150.yaml
eagerx_interbotix/xseries/assets/config/rx200.yaml
eagerx_interbotix-0.1.11.dist-info/LICENSE
eagerx_interbotix-0.1.11.dist-info/METADATA
eagerx_interbotix-0.1.11.dist-info/WHEEL
eagerx_interbotix-0.1.11.dist-info/RECORD
