Metadata-Version: 2.1
Name: eagerx_interbotix
Version: 0.1.11
Summary: EAGERx interface to interbotix robot arms.
Home-page: https://github.com/eager-dev/eagerx_interbotix
License: Apache2.0
Author: Jelle Luijkx
Author-email: j.d.luijkx@tudelft.nl
Requires-Python: >=3.8,<4.0
Classifier: License :: Other/Proprietary License
Classifier: Programming Language :: Python :: 3
Classifier: Programming Language :: Python :: 3.8
Classifier: Programming Language :: Python :: 3.9
Classifier: Programming Language :: Python :: 3.10
Classifier: Programming Language :: Python :: 3.11
Requires-Dist: eagerx (>=0.1.38,<0.2.0)
Requires-Dist: eagerx-pybullet (>=0.1.11,<0.2.0)
Requires-Dist: eagerx-reality (>=0.1.12,<0.2.0)
Requires-Dist: modern_robotics (>=1.1.0,<2.0.0)
Requires-Dist: opencv-contrib-python (>=4.6.0,<5.0.0)
Requires-Dist: scipy (>=1.0,<2.0)
Requires-Dist: urdf-parser-py (>=0.0.4,<0.0.5)
Requires-Dist: xacro (>=1.13.3,<2.0.0)
Project-URL: Documentation, https://eagerx.readthedocs.io/en/master/
Project-URL: Repository, https://github.com/eager-dev/eagerx_interbotix
